LICENSE
MANIFEST.in
README.md
requirements-dev.txt
requirements.txt
setup.cfg
setup.py
cistatus/__init__.py
cistatus/cli.py
cistatus/providers.py
cistatus/version.py
cistatus.egg-info/PKG-INFO
cistatus.egg-info/SOURCES.txt
cistatus.egg-info/dependency_links.txt
cistatus.egg-info/entry_points.txt
cistatus.egg-info/not-zip-safe
cistatus.egg-info/requires.txt
cistatus.egg-info/top_level.txt